pyriodicity/__init__.py
pyriodicity/_internal/__init__.py
pyriodicity/_internal/online_helper.py
pyriodicity/_internal/utils.py
pyriodicity/online/__init__.py
pyriodicity/online/online_acf.py
pyriodicity/online/online_fft.py
pyriodicity/static/__init__.py
pyriodicity/static/acf.py
pyriodicity/static/autoperiod.py
pyriodicity/static/cfd_autoperiod.py
pyriodicity/static/fft.py
pyriodicity/static/robustperiod.py
pyriodicity/static/sazed.py
pyriodicity-0.6.2.dist-info/METADATA
pyriodicity-0.6.2.dist-info/WHEEL
pyriodicity-0.6.2.dist-info/licenses/LICENSE
pyriodicity-0.6.2.dist-info/RECORD
