Metadata-Version: 2.4
Name: pyriodicity
Version: 0.6.2
Summary: Pyriodicity provides an intuitive and efficient Python implementation of periodicity length detection methods in univariate signals.
License-Expression: MIT
License-File: LICENSE
Keywords: period,periodicity,seasonality,period-detection,periodicity-analysis,seasonality-analysis,autoperiod,cfd-autoperiod,robustperiod,sazed,signal-processing,time-series-analysis
Author: Iskander Gaba
Author-email: iskander@hey.com
Requires-Python: >=3.10
Classifier: Programming Language :: Python :: 3
Classifier: Programming Language :: Python :: 3.10
Classifier: Programming Language :: Python :: 3.11
Classifier: Programming Language :: Python :: 3.12
Classifier: Programming Language :: Python :: 3.13
Classifier: Programming Language :: Python :: 3.14
Requires-Dist: pywavelets (>=1.8,<2.0)
Requires-Dist: scipy (>=1.14,<2.0)
Project-URL: Documentation, https://pyriodicity.readthedocs.io
Project-URL: Repository, https://github.com/iskandergaba/pyriodicity
